gaston/__init__.py
gaston/__main__.py
gaston/binning_and_plotting.py
gaston/cluster_plotting.py
gaston/dp_related.py
gaston/filter_genes.py
gaston/isodepth_scaling.py
gaston/model_selection.py
gaston/neural_net.py
gaston/parse_adata.py
gaston/plot_cell_types.py
gaston/pos_encoding.py
gaston/process_NN_output.py
gaston/restrict_spots.py
gaston/run_slurm_scripts.py
gaston/segmented_fit.py
gaston/spatial_gene_classification.py
gaston_spatial-0.0.3.dist-info/licenses/LICENSE
gaston_spatial-0.0.3.dist-info/METADATA
gaston_spatial-0.0.3.dist-info/WHEEL
gaston_spatial-0.0.3.dist-info/entry_points.txt
gaston_spatial-0.0.3.dist-info/top_level.txt
gaston_spatial-0.0.3.dist-info/RECORD
