Metadata-Version: 2.4
Name: gaston-spatial
Version: 0.0.3
Summary: GASTON: interpretable deep learning model for spatial transcriptomics
Home-page: https://github.com/raphael-group/GASTON
Author: Uthsav Chitra
Author-email: Uthsav Chitra <uchitra@princeton.edu>, Brian Arnold <brianjohnarnold@gmail.com>, Hirak Sarkar <hirak@princeton.edu>, Cong Ma <congma@princeton.edu>, Ben Raphael <braphael@cs.princeton.edu>
License: BSD
Project-URL: Homepage, https://github.com/raphael-group/GASTON
Keywords: spatial transcriptomics,neural network,tissue layer
Platform: Linux
Platform: MacOs
Platform: Windows
Classifier: Programming Language :: Python :: 3
Classifier: License :: OSI Approved :: BSD License
Classifier: Operating System :: OS Independent
Requires-Python: >=3.8
License-File: LICENSE
Requires-Dist: torch
Requires-Dist: matplotlib
Requires-Dist: pandas
Requires-Dist: scikit-learn
Requires-Dist: numpy
Requires-Dist: jupyterlab
Requires-Dist: seaborn
Requires-Dist: tqdm
Requires-Dist: scipy
Provides-Extra: docs
Requires-Dist: ipython; extra == "docs"
Requires-Dist: ipywidgets>=8.0.0; extra == "docs"
Requires-Dist: sphinx>=5.3; extra == "docs"
Requires-Dist: sphinx-autodoc-annotation; extra == "docs"
Requires-Dist: sphinx-autodoc-typehints>=1.10.3; extra == "docs"
Requires-Dist: sphinx_rtd_theme; extra == "docs"
Requires-Dist: sphinxcontrib-bibtex>=2.3.0; extra == "docs"
Requires-Dist: sphinxcontrib-spelling>=7.6.2; extra == "docs"
Requires-Dist: nbsphinx>=0.8.1; extra == "docs"
Requires-Dist: myst-nb>=0.17.1; extra == "docs"
Requires-Dist: sphinx_copybutton>=0.5.0; extra == "docs"
Dynamic: author
Dynamic: home-page
Dynamic: license-file
Dynamic: platform
Dynamic: requires-python
